altxria/janus/core/errors.py
altxria/janus/core/schema_versioning.py
altxria/janus/core/serializer.py
altxria/janus/core/validator.py
altxria/janus/utils/validators.py
janus_validation-0.1.1.dist-info/LICENSE
janus_validation-0.1.1.dist-info/METADATA
janus_validation-0.1.1.dist-info/WHEEL
janus_validation-0.1.1.dist-info/top_level.txt
janus_validation-0.1.1.dist-info/RECORD
