Metadata-Version: 2.1
Name: janus-validation
Version: 0.1.1
Summary: A Python library for robust data validation, serialization, and schema versioning.
Author-email: "Altxria Inc." <company@altxria.com>
License: MIT
Project-URL: Bug Tracker, https://github.com/altxriainc/janus/issues
Project-URL: Documentation, https://github.com/altxriainc/janus/wiki
Project-URL: Source Code, https://github.com/altxriainc/janus
Keywords: data validation,schema versioning,json,yaml,serialization
Classifier: Development Status :: 3 - Alpha
Classifier: Intended Audience :: Developers
Classifier: License :: OSI Approved :: MIT License
Classifier: Programming Language :: Python :: 3
Classifier: Programming Language :: Python :: 3.7
Classifier: Programming Language :: Python :: 3.8
Classifier: Programming Language :: Python :: 3.9
Classifier: Programming Language :: Python :: 3.10
Classifier: Programming Language :: Python :: 3.11
Classifier: Operating System :: OS Independent
Requires-Python: >=3.7
License-File: LICENSE
Requires-Dist: PyYAML
Provides-Extra: dev
Requires-Dist: pytest>=7.0; extra == "dev"
Requires-Dist: black>=23.0; extra == "dev"
Requires-Dist: flake8>=6.0; extra == "dev"
